{
  "project_info": {
    "project_number": "809593708567",
    "project_id": "liquor-information-app",
    "storage_bucket": "liquor-information-app.appspot.com"
  },
  "client": [
    {
      "client_info": {
        "mobilesdk_app_id": "1:809593708567:android:7969d9b61c893053903c52",
        "android_client_info": {
          "package_name": "gahyung.lipurInformationApp"
        }
      },
      "oauth_client": [
        {
          "client_id": "809593708567-1gb55d43ab60e8eitaqg8kjo1r77osgu.apps.googleusercontent.com",
          "client_type": 3
        }
      ],
      "api_key": [
        {
          "current_key": "AIzaSyC4fLlz-HkavU32Y5PqnIWFY27_3kgyIEE"
        }
      ],
      "services": {
        "appinvite_service": {
          "other_platform_oauth_client": [
            {
              "client_id": "809593708567-1gb55d43ab60e8eitaqg8kjo1r77osgu.apps.googleusercontent.com",
              "client_type": 3
            }
          ]
        }
      }
    }
  ],
  "configuration_version": "1"
}